excel_to_json_converter/__init__.py
excel_to_json_converter/converter.py
excel_to_json_converter-0.1.0.dist-info/METADATA
excel_to_json_converter-0.1.0.dist-info/WHEEL
excel_to_json_converter-0.1.0.dist-info/top_level.txt
excel_to_json_converter-0.1.0.dist-info/RECORD
