Metadata-Version: 2.1
Name: excel-to-json-converter
Version: 0.1.0
Summary: A simple library to convert Excel sheets to JSON format by Ksr小熙
Home-page: https://github.com/Future0537/Ksr_SHARE/tree/main/excel_to_json_converter
Author: Ksr小熙
Author-email: 
Classifier: Programming Language :: Python :: 3
Classifier: License :: OSI Approved :: MIT License
Classifier: Operating System :: OS Independent
Requires-Python: >=3.6
Requires-Dist: pandas
